TeamWebQaUPT/__init__.py
TeamWebQaUPT/conftest.py
TeamWebQaUPT/pytest.ini
TeamWebQaUPT/runner.py
TeamWebQaUPT/utils.py
TeamWebQaUPT/webdriver_config.py
TeamWebQaUPT/Features/acercade.feature
TeamWebQaUPT/Features/equipos.feature
TeamWebQaUPT/Features/eventos.feature
TeamWebQaUPT/Features/home.feature
TeamWebQaUPT/Features/lugares.feature
TeamWebQaUPT/Features/participantes.feature
TeamWebQaUPT/Features/steps/__init__.py
TeamWebQaUPT/Features/steps/test_equipos_steps.py
TeamWebQaUPT/Features/steps/test_eventos_steps.py
TeamWebQaUPT/Features/steps/test_home_steps.py
TeamWebQaUPT/Features/steps/test_lugares_steps.py
TeamWebQaUPT/Features/steps/test_participantes_steps.py
TeamWebQaUPT/Features/steps/teste_acercade_steps.py
Tests/__init__.py
Tests/test_runner.py
Tests/test_utils.py
Tests/test_webdriver_config.py
tests/__init__.py
tests/test_runner.py
tests/test_utils.py
TeamWebQaUPT-1.1.32.dist-info/METADATA
TeamWebQaUPT-1.1.32.dist-info/WHEEL
TeamWebQaUPT-1.1.32.dist-info/entry_points.txt
TeamWebQaUPT-1.1.32.dist-info/top_level.txt
TeamWebQaUPT-1.1.32.dist-info/RECORD
