Metadata-Version: 2.1
Name: TeamWebQaUPT
Version: 1.1.32
Summary: Paquete para pruebas automatizadas de interfaces web
Home-page: https://github.com/UPT-FAING-EPIS/proyecto-si8811a-2024-ii-u2-qa-pruebas-valverde-cano
Author: Jean Valverde y Anthony Cano
Author-email: jeanvalverdezamora@gmail.com
Classifier: Programming Language :: Python :: 3
Classifier: License :: OSI Approved :: MIT License
Classifier: Operating System :: OS Independent
Requires-Python: >=3.7
Requires-Dist: selenium>=4.8.0
Requires-Dist: pytest>=7.0.0
Requires-Dist: pytest-xdist>=3.0.0
Requires-Dist: allure-pytest>=2.13.0
